core_system_utils/__init__.py
core_system_utils/energy.py
core_system_utils/filesystem.py
core_system_utils/find_utils.py
core_system_utils/proc_handler.py
core_system_utils/shell.py
core_system_utils/tester.py
core_system_utils-0.0.3.dist-info/METADATA
core_system_utils-0.0.3.dist-info/WHEEL
core_system_utils-0.0.3.dist-info/top_level.txt
core_system_utils-0.0.3.dist-info/RECORD
